django_tailwindcss_automated/__init__.py
django_tailwindcss_automated/main.py
django_tailwindcss_automated-1.0.dist-info/LICENSE
django_tailwindcss_automated-1.0.dist-info/METADATA
django_tailwindcss_automated-1.0.dist-info/WHEEL
django_tailwindcss_automated-1.0.dist-info/entry_points.txt
django_tailwindcss_automated-1.0.dist-info/top_level.txt
django_tailwindcss_automated-1.0.dist-info/RECORD
