Metadata-Version: 2.1
Name: django_tailwindcss_automated
Version: 1.0
Summary: Handles all setup and configuration automatically.
Author: mwwlean(leander)
License: MIT
License-File: LICENSE
